Metadata-Version: 1.0
Name: MockBot
Version: 1.0.0
Summary: A Groupme Bot that Mocks a specified user.
Home-page: https://github.com/dgisolfi/MockBot
Author: dgisolfi
Author-email: UNKNOWN
License: MIT
Platform: UNKNOWN
